mpaws/__init__.py
mpaws/logger.py
mpaws-1.0.0.dist-info/METADATA
mpaws-1.0.0.dist-info/WHEEL
mpaws-1.0.0.dist-info/entry_points.txt
mpaws-1.0.0.dist-info/licenses/LICENSE
mpaws-1.0.0.dist-info/RECORD
