Metadata-Version: 2.4
Name: mpaws
Version: 1.0.0
Summary: Execute AWS CLI across multiple profiles and multiple regions in one go
License: Apache-2.0
License-File: LICENSE
Keywords: mpaws,aws,cli,multi,multiple,profiles,regions
Author: Cliffano Subagio
Author-email: cliffano@gmail.com
Requires-Python: >=3.10,<4.0
Classifier: License :: OSI Approved :: Apache Software License
Classifier: Operating System :: OS Independent
Classifier: Programming Language :: Python :: 3
Classifier: Programming Language :: Python :: 3.10
Classifier: Programming Language :: Python :: 3.11
Classifier: Programming Language :: Python :: 3.12
Classifier: Programming Language :: Python :: 3.13
Classifier: Programming Language :: Python :: 3.14
Requires-Dist: boto3 (>=1.38.27,<1.39.0)
Requires-Dist: click (>=8.3.1,<8.4.0)
Requires-Dist: conflog (>=2.1.0,<2.2.0)
Project-URL: Documentation, https://github.com/cliffano/mpaws
Project-URL: Homepage, https://github.com/cliffano/mpaws
Project-URL: Repository, https://github.com/cliffano/mpaws
